<?xml version="1.0" encoding="UTF-8"?><Bundle xmlns="http://hl7.org/fhir"><type value="collection"/><entry><resource><OperationOutcome><issue><extension url="http://hl7.org/fhir/StructureDefinition/operationoutcome-issue-source"><valueCode value="Publisher"/></extension><severity value="warning"/><code value="not-found"/><details><text value="The HTML fragment 'ip-statements.xhtml' is not included anywhere in the produced implementation guide"/></details><expression value="1"/></issue><issue><extension url="http://hl7.org/fhir/StructureDefinition/operationoutcome-issue-source"><valueCode value="Publisher"/></extension><severity value="warning"/><code value="not-found"/><details><text value="An HTML fragment from the set [cross-version-analysis.xhtml, cross-version-analysis-inline.xhtml] is not included anywhere in the produced implementation guide"/></details><expression value="2"/></issue><issue><extension url="http://hl7.org/fhir/StructureDefinition/operationoutcome-issue-source"><valueCode value="Publisher"/></extension><severity value="warning"/><code value="not-found"/><details><text value="An HTML fragment from the set [dependency-table.xhtml, dependency-table-short.xhtml] is not included anywhere in the produced implementation guide"/></details><expression value="3"/></issue><issue><extension url="http://hl7.org/fhir/StructureDefinition/operationoutcome-issue-source"><valueCode value="Publisher"/></extension><severity value="warning"/><code value="not-found"/><details><text value="The HTML fragment 'globals-table.xhtml' is not included anywhere in the produced implementation guide"/></details><expression value="4"/></issue></OperationOutcome></resource></entry><entry><resource><OperationOutcome><extension url="http://hl7.org/fhir/StructureDefinition/operationoutcome-file"><valueString value="/Users/kohe/GitHub/clinical-core/fsh-generated/resources/ImplementationGuide-clinical-core-set"/></extension><issue><extension url="http://hl7.org/fhir/StructureDefinition/operationoutcome-issue-line"><valueInteger value="1"/></extension><extension url="http://hl7.org/fhir/StructureDefinition/operationoutcome-issue-col"><valueInteger value="987"/></extension><extension url="http://hl7.org/fhir/StructureDefinition/operationoutcome-issue-source"><valueCode value="InstanceValidator"/></extension><extension url="http://hl7.org/fhir/StructureDefinition/operationoutcome-message-id"><valueCode value="Terminology_TX_System_NotKnown"/></extension><severity value="information"/><code value="unknown"/><details><text value="Code System URI 'urn:iso:std:iso:3166-2' is unknown so the code cannot be validated"/></details><expression value="ImplementationGuide/clinical-core-set: ImplementationGuide.jurisdiction[0].coding[0]"/></issue></OperationOutcome></resource></entry><entry><resource><OperationOutcome><extension url="http://hl7.org/fhir/StructureDefinition/operationoutcome-file"><valueString value="/Users/kohe/GitHub/clinical-core/fsh-generated/resources/StructureDefinition-JP-Patient-ccs"/></extension><issue><extension url="http://hl7.org/fhir/StructureDefinition/operationoutcome-issue-source"><valueCode value="ProfileValidator"/></extension><extension url="http://hl7.org/fhir/StructureDefinition/operationoutcome-message-id"><valueCode value="RESOURCE_CANONICAL_MISMATCH"/></extension><severity value="error"/><code value="structure"/><details><text value="Conformance resource /Users/kohe/GitHub/clinical-core/fsh-generated/resources/StructureDefinition-JP-Patient-ccs.json - the canonical URL (http://jpfhir.jp/fhir/ccs/StructureDefinition/JP-Patient-ccs) does not match the URL (http://jpfhir.jp/fhir/eClinicalSummary/StructureDefinition/JP_Patient_ccs)"/></details><expression value="StructureDefinition.where(url = 'http://jpfhir.jp/fhir/eClinicalSummary/StructureDefinition/JP_Patient_ccs')"/></issue><issue><extension url="http://hl7.org/fhir/StructureDefinition/operationoutcome-issue-line"><valueInteger value="1"/></extension><extension url="http://hl7.org/fhir/StructureDefinition/operationoutcome-issue-col"><valueInteger value="59486"/></extension><extension url="http://hl7.org/fhir/StructureDefinition/operationoutcome-issue-source"><valueCode value="InstanceValidator"/></extension><extension url="http://hl7.org/fhir/StructureDefinition/operationoutcome-message-id"><valueCode value="Terminology_TX_System_NotKnown"/></extension><severity value="information"/><code value="unknown"/><details><text value="Code System URI 'urn:iso:std:iso:3166-2' is unknown so the code cannot be validated"/></details><expression value="StructureDefinition/JP-Patient-ccs: StructureDefinition.jurisdiction[0].coding[0]"/></issue><issue><extension url="http://hl7.org/fhir/StructureDefinition/operationoutcome-issue-line"><valueInteger value="1"/></extension><extension url="http://hl7.org/fhir/StructureDefinition/operationoutcome-issue-col"><valueInteger value="85210"/></extension><extension url="http://hl7.org/fhir/StructureDefinition/operationoutcome-issue-source"><valueCode value="InstanceValidator"/></extension><extension url="http://hl7.org/fhir/StructureDefinition/operationoutcome-message-id"><valueCode value="TYPE_SPECIFIC_CHECKS_DT_MARKDOWN_HTML"/></extension><severity value="warning"/><code value="structure"/><details><text value="The markdown contains content that appears to be an embedded HTML tag starting at 'Th'. This will (or SHOULD) be escaped by the presentation layer. The content should be checked to confirm that this is the desired behaviour"/></details><expression value="StructureDefinition/JP-Patient-ccs: StructureDefinition.snapshot.element[17].comment"/></issue><issue><extension url="http://hl7.org/fhir/StructureDefinition/operationoutcome-issue-source"><valueCode value="Publisher"/></extension><severity value="warning"/><code value="business-rule"/><details><text value="The Implementation Guide contains no examples for this profile"/></details><expression value="StructureDefinition.where(url = 'http://jpfhir.jp/fhir/eClinicalSummary/StructureDefinition/JP_Patient_ccs')"/></issue><issue><extension url="http://hl7.org/fhir/StructureDefinition/operationoutcome-issue-source"><valueCode value="Publisher"/></extension><severity value="error"/><code value="business-rule"/><details><text value="URL Mismatch http://jpfhir.jp/fhir/ccs/StructureDefinition/JP-Patient-ccs vs http://jpfhir.jp/fhir/eClinicalSummary/StructureDefinition/JP_Patient_ccs"/></details><expression value="/Users/kohe/GitHub/clinical-core/fsh-generated/resources/StructureDefinition-JP-Patient-ccs"/></issue></OperationOutcome></resource></entry></Bundle>