{
  "resourceType": "Patient",
  "id": "Example-JP-Patient-minimun",
  "meta": {
    "lastUpdated": "2023-04-01T10:00:00+09:00",
    "profile": [
      "http://jpfhir.jp/fhir/core/StructureDefinition/JP_Patient"
    ]
  },
  "language": "ja",
  "identifier": [
    {
      "system": "http://jpfhir.jp/fhir/eCS/Idsystem/JP_Hospital_PatientID",
      "value": "000999739"
    },
    {
      "system": "http://jpfhir.jp/fhir/clins/Idsystem/JP_Insurance_memberID",
      "value": "00012345:あいう:１８７:05"
    }
  ]
}
